{"timestamp": "2026-03-13T14:26:32.608717", "frame": "frame_0.jpg", "data": "[VIOLATION] Mandatory gloves for ready-to-eat food"}
{"timestamp": "2026-03-13T14:26:37.018194", "frame": "frame_1.jpg", "data": "VIOLATION: Mandatory hairnet and Mandatory gloves"}
{"timestamp": "2026-03-13T14:26:40.900020", "frame": "frame_10.jpg", "data": "VIOLATION - Mandatory hairnets and beard guards; Mandatory gloves for ready-to-eat food"}
{"timestamp": "2026-03-13T14:26:44.894488", "frame": "frame_11.jpg", "data": "VIOLATION: Mandatory hairnets and beard guards"}
{"timestamp": "2026-03-13T14:26:49.195800", "frame": "frame_12.jpg", "data": "[VIOLATION] Hairnet, Gloves"}
{"timestamp": "2026-03-13T14:26:53.496429", "frame": "frame_13.jpg", "data": "VIOLATION: Mandatory hairnets and beard guards"}
{"timestamp": "2026-03-13T14:26:56.895407", "frame": "frame_14.jpg", "data": "VIOLATION: Mandatory hairnets and beard guards"}
{"timestamp": "2026-03-13T14:27:01.483779", "frame": "frame_15.jpg", "data": "VIOLATION: Mandatory hairnets and beard guards."}
{"timestamp": "2026-03-13T14:27:06.092090", "frame": "frame_16.jpg", "data": "[VIOLATION] [Mandatory hairnets and beard guards]"}
{"timestamp": "2026-03-13T14:27:09.777015", "frame": "frame_17.jpg", "data": "VIOLATION: Mandatory hairnets and beard guards, Mandatory gloves for ready-to-eat food"}
{"timestamp": "2026-03-13T14:27:14.008955", "frame": "frame_18.jpg", "data": "VIOLATION: Mandatory hairnets and beard guards; Mandatory gloves for ready-to-eat food"}
{"timestamp": "2026-03-13T14:27:17.454634", "frame": "frame_19.jpg", "data": "[VIOLATION] Mandatory gloves for ready-to-eat food"}
{"timestamp": "2026-03-13T14:27:21.757475", "frame": "frame_2.jpg", "data": "VIOLATION: Mandatory gloves for ready-to-eat food, Mandatory hairnets and beard guards"}
{"timestamp": "2026-03-13T14:27:25.446221", "frame": "frame_3.jpg", "data": "[VIOLATION] Hairnet and glove policy"}
{"timestamp": "2026-03-13T14:27:30.054219", "frame": "frame_4.jpg", "data": "[VIOLATION] Mandatory gloves for ready-to-eat food"}
{"timestamp": "2026-03-13T14:27:33.457138", "frame": "frame_5.jpg", "data": "[VIOLATION] Mandatory hairnets and beard guards; Mandatory gloves for ready-to-eat food"}
{"timestamp": "2026-03-13T14:27:38.346120", "frame": "frame_6.jpg", "data": "[VIOLATION] Mandatory hairnets and beard guards."}
{"timestamp": "2026-03-13T14:27:41.727289", "frame": "frame_7.jpg", "data": "VIOLATION: Mandatory gloves for ready-to-eat food; Mandatory hairnets"}
{"timestamp": "2026-03-13T14:27:45.411611", "frame": "frame_8.jpg", "data": "VIOLATION: Mandatory hairnets and beard guards; Mandatory gloves for ready-to-eat food"}
{"timestamp": "2026-03-13T14:27:48.793131", "frame": "frame_9.jpg", "data": "VIOLATION: Mandatory hairnets and beard guards, Mandatory gloves for ready-to-eat food"}
